{
  "year": 2012,
  "count": 313,
  "assessments": [
    {
      "id": 2782410,
      "taxonID": 22423,
      "pubYear": 2012,
      "year": 2012,
      "name": "Tryonia brunei",
      "kingdom": "ANIMALIA",
      "category": "Critically Endangered",
      "popTrend": "Decreasing",
      "points": null
    },
    {
      "id": 1939580,
      "taxonID": 18990,
      "pubYear": 2012,
      "year": 2012,
      "name": "Pyrgulopsis trivialis",
      "kingdom": "ANIMALIA",
      "category": "Critically Endangered",
      "popTrend": "Decreasing",
      "points": null
    },
    {
      "id": 1939708,
      "taxonID": 18991,
      "pubYear": 2012,
      "year": 2012,
      "name": "Pyrgulopsis bernardina",
      "kingdom": "ANIMALIA",
      "category": "Endangered",
      "popTrend": "Decreasing",
      "points": null
    },
    {
      "id": 2758611,
      "taxonID": 203018,
      "pubYear": 2013,
      "year": 2012,
      "name": "Abronia salvadorensis",
      "kingdom": "ANIMALIA",
      "category": "Endangered",
      "popTrend": "Decreasing",
      "points": null
    },
    {
      "id": 2758583,
      "taxonID": 203014,
      "pubYear": 2013,
      "year": 2012,
      "name": "Abronia campbelli",
      "kingdom": "ANIMALIA",
      "category": "Critically Endangered",
      "popTrend": "Decreasing",
      "points": null
    },
    {
      "id": 501876,
      "taxonID": 11249,
      "pubYear": 2012,
      "year": 2012,
      "name": "Lampsilis abrupta",
      "kingdom": "ANIMALIA",
      "category": "Vulnerable",
      "popTrend": "Decreasing",
      "points": null
    },
    {
      "id": 143160628,
      "taxonID": 9676,
      "pubYear": 2014,
      "year": 2012,
      "name": "Hapalemur alaotrensis",
      "kingdom": "ANIMALIA",
      "category": "Critically Endangered",
      "popTrend": "Decreasing",
      "points": null
    },
    {
      "id": 141792003,
      "taxonID": 39393,
      "pubYear": 2013,
      "year": 2012,
      "name": "Pristis zijsron",
      "kingdom": "ANIMALIA",
      "category": "Critically Endangered",
      "popTrend": "Decreasing",
      "points": null
    },
    {
      "id": 141791261,
      "taxonID": 18175,
      "pubYear": 2013,
      "year": 2012,
      "name": "Pristis pectinata",
      "kingdom": "ANIMALIA",
      "category": "Critically Endangered",
      "popTrend": "Decreasing",
      "points": null
    },
    {
      "id": 141790455,
      "taxonID": 39390,
      "pubYear": 2013,
      "year": 2012,
      "name": "Pristis clavata",
      "kingdom": "ANIMALIA",
      "category": "Endangered",
      "popTrend": "Decreasing",
      "points": null
    },
    {
      "id": 141789456,
      "taxonID": 39389,
      "pubYear": 2013,
      "year": 2012,
      "name": "Anoxypristis cuspidata",
      "kingdom": "ANIMALIA",
      "category": "Endangered",
      "popTrend": "Decreasing",
      "points": null
    },
    {
      "id": 3111385,
      "taxonID": 62262,
      "pubYear": 2012,
      "year": 2012,
      "name": "Epioblasma torulosa",
      "kingdom": "ANIMALIA",
      "category": "Critically Endangered",
      "popTrend": "Decreasing",
      "points": null
    },
    {
      "id": 3130117,
      "taxonID": 63841,
      "pubYear": 2013,
      "year": 2012,
      "name": "Leptophis modestus",
      "kingdom": "ANIMALIA",
      "category": "Vulnerable",
      "popTrend": "Decreasing",
      "points": null
    },
    {
      "id": 3134725,
      "taxonID": 64302,
      "pubYear": 2014,
      "year": 2012,
      "name": "Bothriechis aurifer",
      "kingdom": "ANIMALIA",
      "category": "Vulnerable",
      "popTrend": "Decreasing",
      "points": null
    },
    {
      "id": 3138432,
      "taxonID": 7582,
      "pubYear": 2012,
      "year": 2012,
      "name": "Elimia ampla",
      "kingdom": "ANIMALIA",
      "category": "Critically Endangered",
      "popTrend": "Decreasing",
      "points": null
    },
    {
      "id": 3139176,
      "taxonID": 7598,
      "pubYear": 2012,
      "year": 2012,
      "name": "Elimia varians",
      "kingdom": "ANIMALIA",
      "category": "Vulnerable",
      "popTrend": "Decreasing",
      "points": null
    },
    {
      "id": 3139545,
      "taxonID": 7602,
      "pubYear": 2012,
      "year": 2012,
      "name": "Elimia bellula",
      "kingdom": "ANIMALIA",
      "category": "Endangered",
      "popTrend": "Decreasing",
      "points": null
    },
    {
      "id": 3140024,
      "taxonID": 7631,
      "pubYear": 2012,
      "year": 2012,
      "name": "Elliptio nigella",
      "kingdom": "ANIMALIA",
      "category": "Critically Endangered",
      "popTrend": "Decreasing",
      "points": null
    },
    {
      "id": 3140136,
      "taxonID": 7633,
      "pubYear": 2012,
      "year": 2012,
      "name": "Elliptio spinosa",
      "kingdom": "ANIMALIA",
      "category": "Endangered",
      "popTrend": "Decreasing",
      "points": null
    },
    {
      "id": 3140353,
      "taxonID": 7652,
      "pubYear": 2012,
      "year": 2012,
      "name": "Elliptoideus sloatianus",
      "kingdom": "ANIMALIA",
      "category": "Vulnerable",
      "popTrend": "Decreasing",
      "points": null
    },
    {
      "id": 3142177,
      "taxonID": 773,
      "pubYear": 2012,
      "year": 2012,
      "name": "Alasmidonta arcula",
      "kingdom": "ANIMALIA",
      "category": "Endangered",
      "popTrend": "Decreasing",
      "points": null
    },
    {
      "id": 3142336,
      "taxonID": 774,
      "pubYear": 2012,
      "year": 2012,
      "name": "Alasmidonta atropurpurea",
      "kingdom": "ANIMALIA",
      "category": "Endangered",
      "popTrend": "Decreasing",
      "points": null
    },
    {
      "id": 3142501,
      "taxonID": 776,
      "pubYear": 2012,
      "year": 2012,
      "name": "Alasmidonta raveneliana",
      "kingdom": "ANIMALIA",
      "category": "Critically Endangered",
      "popTrend": "Decreasing",
      "points": null
    },
    {
      "id": 3143774,
      "taxonID": 7866,
      "pubYear": 2012,
      "year": 2012,
      "name": "Epioblasma capsaeformis",
      "kingdom": "ANIMALIA",
      "category": "Endangered",
      "popTrend": "Decreasing",
      "points": null
    },
    {
      "id": 3144015,
      "taxonID": 7877,
      "pubYear": 2012,
      "year": 2012,
      "name": "Epioblasma othcaloogensis",
      "kingdom": "ANIMALIA",
      "category": "Critically Endangered",
      "popTrend": "Decreasing",
      "points": null
    },
    {
      "id": 3146130,
      "taxonID": 8773,
      "pubYear": 2012,
      "year": 2012,
      "name": "Fusconaia cuneolus",
      "kingdom": "ANIMALIA",
      "category": "Endangered",
      "popTrend": "Decreasing",
      "points": null
    },
    {
      "id": 3146358,
      "taxonID": 8775,
      "pubYear": 2012,
      "year": 2012,
      "name": "Fusconaia subrotunda",
      "kingdom": "ANIMALIA",
      "category": "Vulnerable",
      "popTrend": "Decreasing",
      "points": null
    },
    {
      "id": 3146798,
      "taxonID": 8778,
      "pubYear": 2012,
      "year": 2012,
      "name": "Fusconaia cor",
      "kingdom": "ANIMALIA",
      "category": "Critically Endangered",
      "popTrend": "Decreasing",
      "points": null
    },
    {
      "id": 3147017,
      "taxonID": 8780,
      "pubYear": 2012,
      "year": 2012,
      "name": "Fusconaia lananensis",
      "kingdom": "ANIMALIA",
      "category": "Endangered",
      "popTrend": "Decreasing",
      "points": null
    },
    {
      "id": 509635,
      "taxonID": 12800,
      "pubYear": 2012,
      "year": 2012,
      "name": "Margaritifera marrianae",
      "kingdom": "ANIMALIA",
      "category": "Endangered",
      "popTrend": "Decreasing",
      "points": null
    },
    {
      "id": 3148029,
      "taxonID": 8917,
      "pubYear": 2015,
      "year": 2012,
      "name": "Garra dunsirei",
      "kingdom": "ANIMALIA",
      "category": "Endangered",
      "popTrend": "Stable",
      "points": null
    },
    {
      "id": 61986700,
      "taxonID": 136645,
      "pubYear": 2014,
      "year": 2012,
      "name": "Lepilemur sahamalaza",
      "kingdom": "ANIMALIA",
      "category": "Critically Endangered",
      "popTrend": "Decreasing",
      "points": null
    },
    {
      "id": 62260437,
      "taxonID": 11496,
      "pubYear": 2014,
      "year": 2012,
      "name": "Lemur catta",
      "kingdom": "ANIMALIA",
      "category": "Endangered",
      "popTrend": "Decreasing",
      "points": null
    },
    {
      "id": 504863,
      "taxonID": 11922,
      "pubYear": 2012,
      "year": 2012,
      "name": "Pleuronaia dolabelloides",
      "kingdom": "ANIMALIA",
      "category": "Endangered",
      "popTrend": "Decreasing",
      "points": null
    },
    {
      "id": 166611530,
      "taxonID": 20165,
      "pubYear": 2020,
      "year": 2012,
      "name": "Setonix brachyurus",
      "kingdom": "ANIMALIA",
      "category": "Vulnerable",
      "popTrend": "Decreasing",
      "points": null
    },
    {
      "id": 546965,
      "taxonID": 15021,
      "pubYear": 2012,
      "year": 2012,
      "name": "Obovaria jacksoniana",
      "kingdom": "ANIMALIA",
      "category": "Vulnerable",
      "popTrend": "Decreasing",
      "points": null
    },
    {
      "id": 502943,
      "taxonID": 11479,
      "pubYear": 2012,
      "year": 2012,
      "name": "Lemiox rimosus",
      "kingdom": "ANIMALIA",
      "category": "Critically Endangered",
      "popTrend": "Decreasing",
      "points": null
    },
    {
      "id": 501662,
      "taxonID": 11242,
      "pubYear": 2012,
      "year": 2012,
      "name": "Lampsilis rafinesqueana",
      "kingdom": "ANIMALIA",
      "category": "Endangered",
      "popTrend": "Decreasing",
      "points": null
    },
    {
      "id": 1074877,
      "taxonID": 16479,
      "pubYear": 2012,
      "year": 2012,
      "name": "Pegias fabula",
      "kingdom": "ANIMALIA",
      "category": "Critically Endangered",
      "popTrend": "Decreasing",
      "points": null
    },
    {
      "id": 70621612,
      "taxonID": 62202,
      "pubYear": 2014,
      "year": 2012,
      "name": "Lepidomeda mollispinis",
      "kingdom": "ANIMALIA",
      "category": "Vulnerable",
      "popTrend": "Stable",
      "points": null
    },
    {
      "id": 1107712,
      "taxonID": 166043,
      "pubYear": 2012,
      "year": 2012,
      "name": "Luciocyprinus langsoni",
      "kingdom": "ANIMALIA",
      "category": "Vulnerable",
      "popTrend": "Decreasing",
      "points": null
    },
    {
      "id": 13151682,
      "taxonID": 13151680,
      "pubYear": 2012,
      "year": 2012,
      "name": "Hucho bleekeri",
      "kingdom": "ANIMALIA",
      "category": "Critically Endangered",
      "popTrend": "Decreasing",
      "points": null
    },
    {
      "id": 13152070,
      "taxonID": 13152063,
      "pubYear": 2013,
      "year": 2012,
      "name": "Tarentola boavistensis",
      "kingdom": "ANIMALIA",
      "category": "Vulnerable",
      "popTrend": "Decreasing",
      "points": null
    },
    {
      "id": 13152180,
      "taxonID": 13152177,
      "pubYear": 2013,
      "year": 2012,
      "name": "Tarentola gigas",
      "kingdom": "ANIMALIA",
      "category": "Endangered",
      "popTrend": "Stable",
      "points": null
    },
    {
      "id": 13322840,
      "taxonID": 136007,
      "pubYear": 2015,
      "year": 2012,
      "name": "Nectophrynoides paulae",
      "kingdom": "ANIMALIA",
      "category": "Critically Endangered",
      "popTrend": "Decreasing",
      "points": null
    },
    {
      "id": 13324673,
      "taxonID": 13322492,
      "pubYear": 2012,
      "year": 2012,
      "name": "Dasypoda frieseana",
      "kingdom": "ANIMALIA",
      "category": "Endangered",
      "popTrend": "Decreasing",
      "points": null
    },
    {
      "id": 13339966,
      "taxonID": 13325442,
      "pubYear": 2013,
      "year": 2012,
      "name": "Halictus carinthiacus",
      "kingdom": "ANIMALIA",
      "category": "Endangered",
      "popTrend": "Decreasing",
      "points": null
    },
    {
      "id": 13340090,
      "taxonID": 13338098,
      "pubYear": 2013,
      "year": 2012,
      "name": "Halictus microcardia",
      "kingdom": "ANIMALIA",
      "category": "Endangered",
      "popTrend": "Decreasing",
      "points": null
    },
    {
      "id": 13508504,
      "taxonID": 13508501,
      "pubYear": 2012,
      "year": 2012,
      "name": "Rhinopithecus strykeri",
      "kingdom": "ANIMALIA",
      "category": "Critically Endangered",
      "popTrend": "Decreasing",
      "points": null
    },
    {
      "id": 14665385,
      "taxonID": 14665363,
      "pubYear": 2012,
      "year": 2012,
      "name": "Lygodactylus williamsi",
      "kingdom": "ANIMALIA",
      "category": "Critically Endangered",
      "popTrend": "Decreasing",
      "points": null
    },
    {
      "id": 14857036,
      "taxonID": 44189,
      "pubYear": 2012,
      "year": 2012,
      "name": "Ctenosaura melanosterna",
      "kingdom": "ANIMALIA",
      "category": "Endangered",
      "popTrend": "Decreasing",
      "points": null
    },
    {
      "id": 15181011,
      "taxonID": 20380,
      "pubYear": 2013,
      "year": 2012,
      "name": "Sechellophryne gardineri",
      "kingdom": "ANIMALIA",
      "category": "Endangered",
      "popTrend": "Decreasing",
      "points": null
    },
    {
      "id": 2744223,
      "taxonID": 202419,
      "pubYear": 2014,
      "year": 2012,
      "name": "Rhadinella pegosalyta",
      "kingdom": "ANIMALIA",
      "category": "Vulnerable",
      "popTrend": "Decreasing",
      "points": null
    },
    {
      "id": 15446818,
      "taxonID": 20381,
      "pubYear": 2013,
      "year": 2012,
      "name": "Sooglossus sechellensis",
      "kingdom": "ANIMALIA",
      "category": "Endangered",
      "popTrend": "Decreasing",
      "points": null
    },
    {
      "id": 15603615,
      "taxonID": 15522229,
      "pubYear": 2015,
      "year": 2012,
      "name": "Merluccius senegalensis",
      "kingdom": "ANIMALIA",
      "category": "Endangered",
      "popTrend": "Decreasing",
      "points": null
    },
    {
      "id": 16111169,
      "taxonID": 868,
      "pubYear": 2014,
      "year": 2012,
      "name": "Allocebus trichotis",
      "kingdom": "ANIMALIA",
      "category": "Vulnerable",
      "popTrend": "Decreasing",
      "points": null
    },
    {
      "id": 16112577,
      "taxonID": 41576,
      "pubYear": 2014,
      "year": 2012,
      "name": "Cheirogaleus sibreei",
      "kingdom": "ANIMALIA",
      "category": "Critically Endangered",
      "popTrend": "Decreasing",
      "points": null
    },
    {
      "id": 16112746,
      "taxonID": 41573,
      "pubYear": 2014,
      "year": 2012,
      "name": "Microcebus berthae",
      "kingdom": "ANIMALIA",
      "category": "Endangered",
      "popTrend": "Decreasing",
      "points": null
    },
    {
      "id": 16112834,
      "taxonID": 136537,
      "pubYear": 2014,
      "year": 2012,
      "name": "Microcebus bongolavensis",
      "kingdom": "ANIMALIA",
      "category": "Endangered",
      "popTrend": "Decreasing",
      "points": null
    },
    {
      "id": 16112905,
      "taxonID": 136347,
      "pubYear": 2014,
      "year": 2012,
      "name": "Microcebus danfossi",
      "kingdom": "ANIMALIA",
      "category": "Endangered",
      "popTrend": "Decreasing",
      "points": null
    },
    {
      "id": 16113044,
      "taxonID": 136458,
      "pubYear": 2014,
      "year": 2012,
      "name": "Microcebus jollyae",
      "kingdom": "ANIMALIA",
      "category": "Endangered",
      "popTrend": "Decreasing",
      "points": null
    },
    {
      "id": 16113109,
      "taxonID": 136199,
      "pubYear": 2014,
      "year": 2012,
      "name": "Microcebus lehilahytsara",
      "kingdom": "ANIMALIA",
      "category": "Vulnerable",
      "popTrend": "Decreasing",
      "points": null
    },
    {
      "id": 16113183,
      "taxonID": 136206,
      "pubYear": 2014,
      "year": 2012,
      "name": "Microcebus mamiratra",
      "kingdom": "ANIMALIA",
      "category": "Critically Endangered",
      "popTrend": "Decreasing",
      "points": null
    },
    {
      "id": 16113275,
      "taxonID": 136272,
      "pubYear": 2014,
      "year": 2012,
      "name": "Microcebus mittermeieri",
      "kingdom": "ANIMALIA",
      "category": "Endangered",
      "popTrend": "Decreasing",
      "points": null
    },
    {
      "id": 16113437,
      "taxonID": 13325,
      "pubYear": 2014,
      "year": 2012,
      "name": "Microcebus myoxinus",
      "kingdom": "ANIMALIA",
      "category": "Vulnerable",
      "popTrend": "Decreasing",
      "points": null
    },
    {
      "id": 16113536,
      "taxonID": 39751,
      "pubYear": 2014,
      "year": 2012,
      "name": "Microcebus ravelobensis",
      "kingdom": "ANIMALIA",
      "category": "Endangered",
      "popTrend": "Decreasing",
      "points": null
    },
    {
      "id": 16113616,
      "taxonID": 59544947,
      "pubYear": 2014,
      "year": 2012,
      "name": "Microcebus rufus",
      "kingdom": "ANIMALIA",
      "category": "Vulnerable",
      "popTrend": "Decreasing",
      "points": null
    },
    {
      "id": 16113693,
      "taxonID": 41572,
      "pubYear": 2014,
      "year": 2012,
      "name": "Microcebus sambiranensis",
      "kingdom": "ANIMALIA",
      "category": "Endangered",
      "popTrend": "Decreasing",
      "points": null
    },
    {
      "id": 16113787,
      "taxonID": 136744,
      "pubYear": 2014,
      "year": 2012,
      "name": "Microcebus simmonsi",
      "kingdom": "ANIMALIA",
      "category": "Endangered",
      "popTrend": "Decreasing",
      "points": null
    },
    {
      "id": 16113861,
      "taxonID": 41571,
      "pubYear": 2014,
      "year": 2012,
      "name": "Microcebus tavaratra",
      "kingdom": "ANIMALIA",
      "category": "Vulnerable",
      "popTrend": "Decreasing",
      "points": null
    },
    {
      "id": 16113952,
      "taxonID": 13584,
      "pubYear": 2014,
      "year": 2012,
      "name": "Mirza coquereli",
      "kingdom": "ANIMALIA",
      "category": "Endangered",
      "popTrend": "Decreasing",
      "points": null
    },
    {
      "id": 16114079,
      "taxonID": 136684,
      "pubYear": 2014,
      "year": 2012,
      "name": "Mirza zaza",
      "kingdom": "ANIMALIA",
      "category": "Endangered",
      "popTrend": "Decreasing",
      "points": null
    },
    {
      "id": 16114199,
      "taxonID": 16875,
      "pubYear": 2014,
      "year": 2012,
      "name": "Phaner electromontis",
      "kingdom": "ANIMALIA",
      "category": "Endangered",
      "popTrend": "Decreasing",
      "points": null
    },
    {
      "id": 16114295,
      "taxonID": 16872,
      "pubYear": 2014,
      "year": 2012,
      "name": "Phaner furcifer",
      "kingdom": "ANIMALIA",
      "category": "Vulnerable",
      "popTrend": "Decreasing",
      "points": null
    },
    {
      "id": 16114392,
      "taxonID": 16874,
      "pubYear": 2014,
      "year": 2012,
      "name": "Phaner pallescens",
      "kingdom": "ANIMALIA",
      "category": "Endangered",
      "popTrend": "Decreasing",
      "points": null
    },
    {
      "id": 16114500,
      "taxonID": 16873,
      "pubYear": 2014,
      "year": 2012,
      "name": "Phaner parienti",
      "kingdom": "ANIMALIA",
      "category": "Endangered",
      "popTrend": "Decreasing",
      "points": null
    },
    {
      "id": 16114609,
      "taxonID": 6302,
      "pubYear": 2014,
      "year": 2012,
      "name": "Daubentonia madagascariensis",
      "kingdom": "ANIMALIA",
      "category": "Endangered",
      "popTrend": "Decreasing",
      "points": null
    },
    {
      "id": 16114766,
      "taxonID": 136767,
      "pubYear": 2014,
      "year": 2012,
      "name": "Avahi betsileo",
      "kingdom": "ANIMALIA",
      "category": "Endangered",
      "popTrend": "Decreasing",
      "points": null
    },
    {
      "id": 16114861,
      "taxonID": 136335,
      "pubYear": 2014,
      "year": 2012,
      "name": "Avahi cleesei",
      "kingdom": "ANIMALIA",
      "category": "Endangered",
      "popTrend": "Decreasing",
      "points": null
    },
    {
      "id": 16114949,
      "taxonID": 2434,
      "pubYear": 2014,
      "year": 2012,
      "name": "Avahi laniger",
      "kingdom": "ANIMALIA",
      "category": "Vulnerable",
      "popTrend": "Decreasing",
      "points": null
    },
    {
      "id": 16115032,
      "taxonID": 136369,
      "pubYear": 2014,
      "year": 2012,
      "name": "Avahi meridionalis",
      "kingdom": "ANIMALIA",
      "category": "Endangered",
      "popTrend": "Decreasing",
      "points": null
    },
    {
      "id": 16115100,
      "taxonID": 2435,
      "pubYear": 2014,
      "year": 2012,
      "name": "Avahi occidentalis",
      "kingdom": "ANIMALIA",
      "category": "Endangered",
      "popTrend": "Decreasing",
      "points": null
    },
    {
      "id": 16115214,
      "taxonID": 136285,
      "pubYear": 2014,
      "year": 2012,
      "name": "Avahi peyrierasi",
      "kingdom": "ANIMALIA",
      "category": "Vulnerable",
      "popTrend": "Decreasing",
      "points": null
    },
    {
      "id": 16115288,
      "taxonID": 136434,
      "pubYear": 2014,
      "year": 2012,
      "name": "Avahi ramanantsoavanai",
      "kingdom": "ANIMALIA",
      "category": "Vulnerable",
      "popTrend": "Decreasing",
      "points": null
    },
    {
      "id": 16115358,
      "taxonID": 41579,
      "pubYear": 2014,
      "year": 2012,
      "name": "Avahi unicolor",
      "kingdom": "ANIMALIA",
      "category": "Endangered",
      "popTrend": "Decreasing",
      "points": null
    },
    {
      "id": 16115457,
      "taxonID": 10826,
      "pubYear": 2014,
      "year": 2012,
      "name": "Indri indri",
      "kingdom": "ANIMALIA",
      "category": "Critically Endangered",
      "popTrend": "Decreasing",
      "points": null
    },
    {
      "id": 16115622,
      "taxonID": 18360,
      "pubYear": 2014,
      "year": 2012,
      "name": "Propithecus candidus",
      "kingdom": "ANIMALIA",
      "category": "Critically Endangered",
      "popTrend": "Decreasing",
      "points": null
    },
    {
      "id": 16115770,
      "taxonID": 18355,
      "pubYear": 2014,
      "year": 2012,
      "name": "Propithecus coquereli",
      "kingdom": "ANIMALIA",
      "category": "Endangered",
      "popTrend": "Decreasing",
      "points": null
    },
    {
      "id": 16115921,
      "taxonID": 18356,
      "pubYear": 2014,
      "year": 2012,
      "name": "Propithecus coronatus",
      "kingdom": "ANIMALIA",
      "category": "Endangered",
      "popTrend": "Decreasing",
      "points": null
    },
    {
      "id": 16116046,
      "taxonID": 18357,
      "pubYear": 2014,
      "year": 2012,
      "name": "Propithecus deckenii",
      "kingdom": "ANIMALIA",
      "category": "Endangered",
      "popTrend": "Decreasing",
      "points": null
    },
    {
      "id": 16116148,
      "taxonID": 18358,
      "pubYear": 2014,
      "year": 2012,
      "name": "Propithecus diadema",
      "kingdom": "ANIMALIA",
      "category": "Critically Endangered",
      "popTrend": "Decreasing",
      "points": null
    },
    {
      "id": 16116270,
      "taxonID": 18359,
      "pubYear": 2014,
      "year": 2012,
      "name": "Propithecus edwardsi",
      "kingdom": "ANIMALIA",
      "category": "Endangered",
      "popTrend": "Decreasing",
      "points": null
    },
    {
      "id": 16116407,
      "taxonID": 18361,
      "pubYear": 2014,
      "year": 2012,
      "name": "Propithecus perrieri",
      "kingdom": "ANIMALIA",
      "category": "Critically Endangered",
      "popTrend": "Decreasing",
      "points": null
    },
    {
      "id": 16116567,
      "taxonID": 18352,
      "pubYear": 2014,
      "year": 2012,
      "name": "Propithecus tattersalli",
      "kingdom": "ANIMALIA",
      "category": "Critically Endangered",
      "popTrend": "Decreasing",
      "points": null
    },
    {
      "id": 16116697,
      "taxonID": 18354,
      "pubYear": 2014,
      "year": 2012,
      "name": "Propithecus verreauxi",
      "kingdom": "ANIMALIA",
      "category": "Endangered",
      "popTrend": "Decreasing",
      "points": null
    },
    {
      "id": 16116806,
      "taxonID": 8204,
      "pubYear": 2014,
      "year": 2012,
      "name": "Eulemur albifrons",
      "kingdom": "ANIMALIA",
      "category": "Endangered",
      "popTrend": "Decreasing",
      "points": null
    },
    {
      "id": 16116926,
      "taxonID": 8205,
      "pubYear": 2014,
      "year": 2012,
      "name": "Eulemur cinereiceps",
      "kingdom": "ANIMALIA",
      "category": "Critically Endangered",
      "popTrend": "Decreasing",
      "points": null
    },
    {
      "id": 16117045,
      "taxonID": 8206,
      "pubYear": 2014,
      "year": 2012,
      "name": "Eulemur collaris",
      "kingdom": "ANIMALIA",
      "category": "Endangered",
      "popTrend": "Decreasing",
      "points": null
    },
    {
      "id": 16117225,
      "taxonID": 8199,
      "pubYear": 2014,
      "year": 2012,
      "name": "Eulemur coronatus",
      "kingdom": "ANIMALIA",
      "category": "Endangered",
      "popTrend": "Decreasing",
      "points": null
    },
    {
      "id": 16117351,
      "taxonID": 8211,
      "pubYear": 2014,
      "year": 2012,
      "name": "Eulemur flavifrons",
      "kingdom": "ANIMALIA",
      "category": "Critically Endangered",
      "popTrend": "Decreasing",
      "points": null
    },
    {
      "id": 16117639,
      "taxonID": 8212,
      "pubYear": 2014,
      "year": 2012,
      "name": "Eulemur macaco",
      "kingdom": "ANIMALIA",
      "category": "Vulnerable",
      "popTrend": "Decreasing",
      "points": null
    },
    {
      "id": 16117799,
      "taxonID": 8202,
      "pubYear": 2014,
      "year": 2012,
      "name": "Eulemur mongoz",
      "kingdom": "ANIMALIA",
      "category": "Critically Endangered",
      "popTrend": "Decreasing",
      "points": null
    },
    {
      "id": 16117921,
      "taxonID": 8203,
      "pubYear": 2014,
      "year": 2012,
      "name": "Eulemur rubriventer",
      "kingdom": "ANIMALIA",
      "category": "Vulnerable",
      "popTrend": "Decreasing",
      "points": null
    },
    {
      "id": 16118167,
      "taxonID": 8209,
      "pubYear": 2014,
      "year": 2012,
      "name": "Eulemur rufus",
      "kingdom": "ANIMALIA",
      "category": "Vulnerable",
      "popTrend": "Decreasing",
      "points": null
    },
    {
      "id": 16118322,
      "taxonID": 8210,
      "pubYear": 2014,
      "year": 2012,
      "name": "Eulemur sanfordi",
      "kingdom": "ANIMALIA",
      "category": "Endangered",
      "popTrend": "Decreasing",
      "points": null
    },
    {
      "id": 16119513,
      "taxonID": 9672,
      "pubYear": 2014,
      "year": 2012,
      "name": "Hapalemur aureus",
      "kingdom": "ANIMALIA",
      "category": "Critically Endangered",
      "popTrend": "Decreasing",
      "points": null
    },
    {
      "id": 16119642,
      "taxonID": 9673,
      "pubYear": 2014,
      "year": 2012,
      "name": "Hapalemur griseus",
      "kingdom": "ANIMALIA",
      "category": "Vulnerable",
      "popTrend": "Decreasing",
      "points": null
    },
    {
      "id": 16119822,
      "taxonID": 136384,
      "pubYear": 2014,
      "year": 2012,
      "name": "Hapalemur meridionalis",
      "kingdom": "ANIMALIA",
      "category": "Vulnerable",
      "popTrend": "Decreasing",
      "points": null
    },
    {
      "id": 16119940,
      "taxonID": 9678,
      "pubYear": 2014,
      "year": 2012,
      "name": "Hapalemur occidentalis",
      "kingdom": "ANIMALIA",
      "category": "Vulnerable",
      "popTrend": "Decreasing",
      "points": null
    },
    {
      "id": 16121559,
      "taxonID": 9674,
      "pubYear": 2014,
      "year": 2012,
      "name": "Prolemur simus",
      "kingdom": "ANIMALIA",
      "category": "Critically Endangered",
      "popTrend": "Decreasing",
      "points": null
    },
    {
      "id": 16121712,
      "taxonID": 22920,
      "pubYear": 2014,
      "year": 2012,
      "name": "Varecia rubra",
      "kingdom": "ANIMALIA",
      "category": "Critically Endangered",
      "popTrend": "Decreasing",
      "points": null
    },
    {
      "id": 16121857,
      "taxonID": 22918,
      "pubYear": 2014,
      "year": 2012,
      "name": "Varecia variegata",
      "kingdom": "ANIMALIA",
      "category": "Critically Endangered",
      "popTrend": "Decreasing",
      "points": null
    },
    {
      "id": 16122166,
      "taxonID": 136376,
      "pubYear": 2014,
      "year": 2012,
      "name": "Lepilemur aeeclis",
      "kingdom": "ANIMALIA",
      "category": "Vulnerable",
      "popTrend": "Decreasing",
      "points": null
    },
    {
      "id": 16122257,
      "taxonID": 136843,
      "pubYear": 2014,
      "year": 2012,
      "name": "Lepilemur ahmansonori",
      "kingdom": "ANIMALIA",
      "category": "Endangered",
      "popTrend": "Decreasing",
      "points": null
    },
    {
      "id": 16122561,
      "taxonID": 136662,
      "pubYear": 2014,
      "year": 2012,
      "name": "Lepilemur betsileo",
      "kingdom": "ANIMALIA",
      "category": "Endangered",
      "popTrend": "Decreasing",
      "points": null
    },
    {
      "id": 16122647,
      "taxonID": 11616,
      "pubYear": 2014,
      "year": 2012,
      "name": "Lepilemur dorsalis",
      "kingdom": "ANIMALIA",
      "category": "Vulnerable",
      "popTrend": "Decreasing",
      "points": null
    },
    {
      "id": 16122761,
      "taxonID": 11617,
      "pubYear": 2014,
      "year": 2012,
      "name": "Lepilemur edwardsi",
      "kingdom": "ANIMALIA",
      "category": "Endangered",
      "popTrend": "Decreasing",
      "points": null
    },
    {
      "id": 16122870,
      "taxonID": 136263,
      "pubYear": 2014,
      "year": 2012,
      "name": "Lepilemur fleuretae",
      "kingdom": "ANIMALIA",
      "category": "Critically Endangered",
      "popTrend": "Decreasing",
      "points": null
    },
    {
      "id": 16122971,
      "taxonID": 136771,
      "pubYear": 2014,
      "year": 2012,
      "name": "Lepilemur grewcockorum",
      "kingdom": "ANIMALIA",
      "category": "Endangered",
      "popTrend": "Decreasing",
      "points": null
    },
    {
      "id": 16123061,
      "taxonID": 136761,
      "pubYear": 2014,
      "year": 2012,
      "name": "Lepilemur hubbardorum",
      "kingdom": "ANIMALIA",
      "category": "Endangered",
      "popTrend": "Decreasing",
      "points": null
    },
    {
      "id": 16123150,
      "taxonID": 136491,
      "pubYear": 2014,
      "year": 2012,
      "name": "Lepilemur jamesorum",
      "kingdom": "ANIMALIA",
      "category": "Critically Endangered",
      "popTrend": "Decreasing",
      "points": null
    },
    {
      "id": 16123261,
      "taxonID": 11618,
      "pubYear": 2014,
      "year": 2012,
      "name": "Lepilemur leucopus",
      "kingdom": "ANIMALIA",
      "category": "Endangered",
      "popTrend": "Decreasing",
      "points": null
    },
    {
      "id": 16123347,
      "taxonID": 11619,
      "pubYear": 2014,
      "year": 2012,
      "name": "Lepilemur microdon",
      "kingdom": "ANIMALIA",
      "category": "Endangered",
      "popTrend": "Decreasing",
      "points": null
    },
    {
      "id": 16123438,
      "taxonID": 136609,
      "pubYear": 2014,
      "year": 2012,
      "name": "Lepilemur milanoii",
      "kingdom": "ANIMALIA",
      "category": "Endangered",
      "popTrend": "Decreasing",
      "points": null
    },
    {
      "id": 16123571,
      "taxonID": 136622,
      "pubYear": 2014,
      "year": 2012,
      "name": "Lepilemur mittermeieri",
      "kingdom": "ANIMALIA",
      "category": "Endangered",
      "popTrend": "Decreasing",
      "points": null
    },
    {
      "id": 16123751,
      "taxonID": 136796,
      "pubYear": 2014,
      "year": 2012,
      "name": "Lepilemur otto",
      "kingdom": "ANIMALIA",
      "category": "Endangered",
      "popTrend": "Decreasing",
      "points": null
    },
    {
      "id": 16123822,
      "taxonID": 136677,
      "pubYear": 2014,
      "year": 2012,
      "name": "Lepilemur petteri",
      "kingdom": "ANIMALIA",
      "category": "Vulnerable",
      "popTrend": "Decreasing",
      "points": null
    },
    {
      "id": 16123894,
      "taxonID": 136254,
      "pubYear": 2014,
      "year": 2012,
      "name": "Lepilemur randrianasoloi",
      "kingdom": "ANIMALIA",
      "category": "Endangered",
      "popTrend": "Decreasing",
      "points": null
    },
    {
      "id": 16123992,
      "taxonID": 11621,
      "pubYear": 2014,
      "year": 2012,
      "name": "Lepilemur ruficaudatus",
      "kingdom": "ANIMALIA",
      "category": "Vulnerable",
      "popTrend": "Decreasing",
      "points": null
    },
    {
      "id": 16124245,
      "taxonID": 136707,
      "pubYear": 2014,
      "year": 2012,
      "name": "Lepilemur seali",
      "kingdom": "ANIMALIA",
      "category": "Vulnerable",
      "popTrend": "Decreasing",
      "points": null
    },
    {
      "id": 16124328,
      "taxonID": 11622,
      "pubYear": 2014,
      "year": 2012,
      "name": "Lepilemur septentrionalis",
      "kingdom": "ANIMALIA",
      "category": "Critically Endangered",
      "popTrend": "Decreasing",
      "points": null
    },
    {
      "id": 16124462,
      "taxonID": 136709,
      "pubYear": 2014,
      "year": 2012,
      "name": "Lepilemur tymerlachsoni",
      "kingdom": "ANIMALIA",
      "category": "Critically Endangered",
      "popTrend": "Decreasing",
      "points": null
    },
    {
      "id": 16124565,
      "taxonID": 136311,
      "pubYear": 2014,
      "year": 2012,
      "name": "Lepilemur wrightae",
      "kingdom": "ANIMALIA",
      "category": "Endangered",
      "popTrend": "Decreasing",
      "points": null
    },
    {
      "id": 16391187,
      "taxonID": 16391176,
      "pubYear": 2013,
      "year": 2012,
      "name": "Marisora roatanae",
      "kingdom": "ANIMALIA",
      "category": "Critically Endangered",
      "popTrend": "Decreasing",
      "points": null
    },
    {
      "id": 2744216,
      "taxonID": 202418,
      "pubYear": 2014,
      "year": 2012,
      "name": "Rhadinella montecristi",
      "kingdom": "ANIMALIA",
      "category": "Vulnerable",
      "popTrend": "Decreasing",
      "points": null
    },
    {
      "id": 16575409,
      "taxonID": 16575406,
      "pubYear": 2015,
      "year": 2012,
      "name": "Arthroleptis bioko",
      "kingdom": "ANIMALIA",
      "category": "Endangered",
      "popTrend": "Decreasing",
      "points": null
    },
    {
      "id": 16664386,
      "taxonID": 10075,
      "pubYear": 2014,
      "year": 2012,
      "name": "Hippocampus kuda",
      "kingdom": "ANIMALIA",
      "category": "Vulnerable",
      "popTrend": "Decreasing",
      "points": null
    },
    {
      "id": 16757701,
      "taxonID": 16757669,
      "pubYear": 2012,
      "year": 2012,
      "name": "Chorthippus bozdaghi",
      "kingdom": "ANIMALIA",
      "category": "Critically Endangered",
      "popTrend": "Decreasing",
      "points": null
    },
    {
      "id": 16757706,
      "taxonID": 16757672,
      "pubYear": 2012,
      "year": 2012,
      "name": "Myrmeleotettix ethicus",
      "kingdom": "ANIMALIA",
      "category": "Critically Endangered",
      "popTrend": "Decreasing",
      "points": null
    },
    {
      "id": 16793120,
      "taxonID": 16793075,
      "pubYear": 2014,
      "year": 2012,
      "name": "Nimbaphrynoides occidentalis",
      "kingdom": "ANIMALIA",
      "category": "Critically Endangered",
      "popTrend": "Stable",
      "points": null
    },
    {
      "id": 16854231,
      "taxonID": 16854228,
      "pubYear": 2015,
      "year": 2012,
      "name": "Cardioglossa manengouba",
      "kingdom": "ANIMALIA",
      "category": "Critically Endangered",
      "popTrend": "Decreasing",
      "points": null
    },
    {
      "id": 16862507,
      "taxonID": 54423,
      "pubYear": 2015,
      "year": 2012,
      "name": "Astylosternus ranoides",
      "kingdom": "ANIMALIA",
      "category": "Endangered",
      "popTrend": "Decreasing",
      "points": null
    },
    {
      "id": 16866334,
      "taxonID": 54410,
      "pubYear": 2014,
      "year": 2012,
      "name": "Cardioglossa trifasciata",
      "kingdom": "ANIMALIA",
      "category": "Critically Endangered",
      "popTrend": "Decreasing",
      "points": null
    },
    {
      "id": 16890395,
      "taxonID": 61542,
      "pubYear": 2013,
      "year": 2012,
      "name": "Philochortus zolii",
      "kingdom": "ANIMALIA",
      "category": "Endangered",
      "popTrend": "Decreasing",
      "points": null
    },
    {
      "id": 16925100,
      "taxonID": 54432,
      "pubYear": 2015,
      "year": 2012,
      "name": "Leptodactylodon erythrogaster",
      "kingdom": "ANIMALIA",
      "category": "Critically Endangered",
      "popTrend": "Decreasing",
      "points": null
    },
    {
      "id": 2790394,
      "taxonID": 29479,
      "pubYear": 2013,
      "year": 2012,
      "name": "Abronia frosti",
      "kingdom": "ANIMALIA",
      "category": "Critically Endangered",
      "popTrend": "Decreasing",
      "points": null
    },
    {
      "id": 16925716,
      "taxonID": 54897,
      "pubYear": 2015,
      "year": 2012,
      "name": "Wolterstorffina chirioi",
      "kingdom": "ANIMALIA",
      "category": "Critically Endangered",
      "popTrend": "Decreasing",
      "points": null
    },
    {
      "id": 16925858,
      "taxonID": 54898,
      "pubYear": 2015,
      "year": 2012,
      "name": "Wolterstorffina mirei",
      "kingdom": "ANIMALIA",
      "category": "Endangered",
      "popTrend": "Decreasing",
      "points": null
    },
    {
      "id": 2791124,
      "taxonID": 19243030,
      "pubYear": 2012,
      "year": 2012,
      "name": "Brachylophus fasciatus",
      "kingdom": "ANIMALIA",
      "category": "Endangered",
      "popTrend": "Decreasing",
      "points": null
    },
    {
      "id": 2791620,
      "taxonID": 2965,
      "pubYear": 2012,
      "year": 2012,
      "name": "Brachylophus vitiensis",
      "kingdom": "ANIMALIA",
      "category": "Critically Endangered",
      "popTrend": "Decreasing",
      "points": null
    },
    {
      "id": 16937397,
      "taxonID": 56091,
      "pubYear": 2013,
      "year": 2012,
      "name": "Callixalus pictus",
      "kingdom": "ANIMALIA",
      "category": "Vulnerable",
      "popTrend": "Decreasing",
      "points": null
    },
    {
      "id": 107350763,
      "taxonID": 54774,
      "pubYear": 2016,
      "year": 2012,
      "name": "Sclerophrys taiensis",
      "kingdom": "ANIMALIA",
      "category": "Endangered",
      "popTrend": "Decreasing",
      "points": null
    },
    {
      "id": 16947326,
      "taxonID": 73343869,
      "pubYear": 2015,
      "year": 2012,
      "name": "Arthroleptis xenodactylus",
      "kingdom": "ANIMALIA",
      "category": "Endangered",
      "popTrend": "Decreasing",
      "points": null
    },
    {
      "id": 16947831,
      "taxonID": 56279,
      "pubYear": 2013,
      "year": 2012,
      "name": "Leptopelis ragazzii",
      "kingdom": "ANIMALIA",
      "category": "Vulnerable",
      "popTrend": "Stable",
      "points": null
    },
    {
      "id": 16948299,
      "taxonID": 56286,
      "pubYear": 2013,
      "year": 2012,
      "name": "Leptopelis yaldeni",
      "kingdom": "ANIMALIA",
      "category": "Vulnerable",
      "popTrend": "Stable",
      "points": null
    },
    {
      "id": 16948437,
      "taxonID": 57703,
      "pubYear": 2013,
      "year": 2012,
      "name": "Balebreviceps hillmani",
      "kingdom": "ANIMALIA",
      "category": "Critically Endangered",
      "popTrend": "Decreasing",
      "points": null
    },
    {
      "id": 16948552,
      "taxonID": 136142,
      "pubYear": 2013,
      "year": 2012,
      "name": "Probreviceps loveridgei",
      "kingdom": "ANIMALIA",
      "category": "Endangered",
      "popTrend": "Stable",
      "points": null
    },
    {
      "id": 16948694,
      "taxonID": 57981,
      "pubYear": 2015,
      "year": 2012,
      "name": "Probreviceps rhodesianus",
      "kingdom": "ANIMALIA",
      "category": "Endangered",
      "popTrend": "Decreasing",
      "points": null
    },
    {
      "id": 16948812,
      "taxonID": 54460,
      "pubYear": 2013,
      "year": 2012,
      "name": "Altiphrynoides malcolmi",
      "kingdom": "ANIMALIA",
      "category": "Endangered",
      "popTrend": "Decreasing",
      "points": null
    },
    {
      "id": 16950012,
      "taxonID": 136057,
      "pubYear": 2015,
      "year": 2012,
      "name": "Nectophrynoides laticeps",
      "kingdom": "ANIMALIA",
      "category": "Critically Endangered",
      "popTrend": "Decreasing",
      "points": null
    },
    {
      "id": 16950768,
      "taxonID": 56061,
      "pubYear": 2013,
      "year": 2012,
      "name": "Afrixalus enseticola",
      "kingdom": "ANIMALIA",
      "category": "Vulnerable",
      "popTrend": "Stable",
      "points": null
    },
    {
      "id": 16951815,
      "taxonID": 56291,
      "pubYear": 2013,
      "year": 2012,
      "name": "Paracassina kounhiensis",
      "kingdom": "ANIMALIA",
      "category": "Vulnerable",
      "popTrend": "Stable",
      "points": null
    },
    {
      "id": 16953411,
      "taxonID": 58512,
      "pubYear": 2013,
      "year": 2012,
      "name": "Ptychadena nana",
      "kingdom": "ANIMALIA",
      "category": "Endangered",
      "popTrend": "Stable",
      "points": null
    },
    {
      "id": 16971368,
      "taxonID": 16971364,
      "pubYear": 2014,
      "year": 2012,
      "name": "Microcebus margotmarshae",
      "kingdom": "ANIMALIA",
      "category": "Endangered",
      "popTrend": "Decreasing",
      "points": null
    },
    {
      "id": 16971393,
      "taxonID": 16971390,
      "pubYear": 2014,
      "year": 2012,
      "name": "Microcebus arnholdi",
      "kingdom": "ANIMALIA",
      "category": "Endangered",
      "popTrend": "Decreasing",
      "points": null
    },
    {
      "id": 16971428,
      "taxonID": 16971425,
      "pubYear": 2014,
      "year": 2012,
      "name": "Microcebus macarthurii",
      "kingdom": "ANIMALIA",
      "category": "Endangered",
      "popTrend": "Decreasing",
      "points": null
    },
    {
      "id": 16971464,
      "taxonID": 16971461,
      "pubYear": 2014,
      "year": 2012,
      "name": "Microcebus gerpi",
      "kingdom": "ANIMALIA",
      "category": "Critically Endangered",
      "popTrend": "Decreasing",
      "points": null
    },
    {
      "id": 16971498,
      "taxonID": 16971489,
      "pubYear": 2014,
      "year": 2012,
      "name": "Lepilemur hollandorum",
      "kingdom": "ANIMALIA",
      "category": "Endangered",
      "popTrend": "Decreasing",
      "points": null
    },
    {
      "id": 16971531,
      "taxonID": 16971518,
      "pubYear": 2014,
      "year": 2012,
      "name": "Lepilemur scottorum",
      "kingdom": "ANIMALIA",
      "category": "Endangered",
      "popTrend": "Decreasing",
      "points": null
    },
    {
      "id": 16971575,
      "taxonID": 16971566,
      "pubYear": 2014,
      "year": 2012,
      "name": "Avahi mooreorum",
      "kingdom": "ANIMALIA",
      "category": "Endangered",
      "popTrend": "Decreasing",
      "points": null
    },
    {
      "id": 107027734,
      "taxonID": 198201,
      "pubYear": 2013,
      "year": 2012,
      "name": "Palaemonetes mexicanus",
      "kingdom": "ANIMALIA",
      "category": "Critically Endangered",
      "popTrend": "Stable",
      "points": null
    },
    {
      "id": 17252219,
      "taxonID": 10087,
      "pubYear": 2015,
      "year": 2012,
      "name": "Hippocampus trimaculatus",
      "kingdom": "ANIMALIA",
      "category": "Vulnerable",
      "popTrend": "Decreasing",
      "points": null
    },
    {
      "id": 18217711,
      "taxonID": 18217620,
      "pubYear": 2012,
      "year": 2012,
      "name": "Grammostola vachoni",
      "kingdom": "ANIMALIA",
      "category": "Vulnerable",
      "popTrend": "Decreasing",
      "points": null
    },
    {
      "id": 18228904,
      "taxonID": 202542,
      "pubYear": 2013,
      "year": 2012,
      "name": "Etheostoma tecumsehi",
      "kingdom": "ANIMALIA",
      "category": "Endangered",
      "popTrend": "Decreasing",
      "points": null
    },
    {
      "id": 18228968,
      "taxonID": 202533,
      "pubYear": 2013,
      "year": 2012,
      "name": "Etheostoma sitikuense",
      "kingdom": "ANIMALIA",
      "category": "Vulnerable",
      "popTrend": "Stable",
      "points": null
    },
    {
      "id": 18229095,
      "taxonID": 10722,
      "pubYear": 2014,
      "year": 2012,
      "name": "Hypomesus transpacificus",
      "kingdom": "ANIMALIA",
      "category": "Critically Endangered",
      "popTrend": "Decreasing",
      "points": null
    },
    {
      "id": 18229201,
      "taxonID": 8890,
      "pubYear": 2013,
      "year": 2012,
      "name": "Gambusia gaigei",
      "kingdom": "ANIMALIA",
      "category": "Vulnerable",
      "popTrend": "Stable",
      "points": null
    },
    {
      "id": 18229582,
      "taxonID": 202530,
      "pubYear": 2013,
      "year": 2012,
      "name": "Etheostoma scotti",
      "kingdom": "ANIMALIA",
      "category": "Endangered",
      "popTrend": "Decreasing",
      "points": null
    },
    {
      "id": 18230026,
      "taxonID": 202132,
      "pubYear": 2013,
      "year": 2012,
      "name": "Lepidomeda aliciae",
      "kingdom": "ANIMALIA",
      "category": "Vulnerable",
      "popTrend": "Decreasing",
      "points": null
    },
    {
      "id": 18231223,
      "taxonID": 202109,
      "pubYear": 2013,
      "year": 2012,
      "name": "Gila seminuda",
      "kingdom": "ANIMALIA",
      "category": "Endangered",
      "popTrend": "Decreasing",
      "points": null
    },
    {
      "id": 18231600,
      "taxonID": 202392,
      "pubYear": 2013,
      "year": 2012,
      "name": "Gambusia clarkhubbsi",
      "kingdom": "ANIMALIA",
      "category": "Vulnerable",
      "popTrend": "Increasing",
      "points": null
    },
    {
      "id": 18231937,
      "taxonID": 9187,
      "pubYear": 2013,
      "year": 2012,
      "name": "Gila intermedia",
      "kingdom": "ANIMALIA",
      "category": "Endangered",
      "popTrend": "Decreasing",
      "points": null
    },
    {
      "id": 18232150,
      "taxonID": 9186,
      "pubYear": 2013,
      "year": 2012,
      "name": "Gila elegans",
      "kingdom": "ANIMALIA",
      "category": "Critically Endangered",
      "popTrend": "Decreasing",
      "points": null
    },
    {
      "id": 18232529,
      "taxonID": 8892,
      "pubYear": 2013,
      "year": 2012,
      "name": "Gambusia heterochir",
      "kingdom": "ANIMALIA",
      "category": "Vulnerable",
      "popTrend": "Stable",
      "points": null
    },
    {
      "id": 18233543,
      "taxonID": 11579,
      "pubYear": 2014,
      "year": 2012,
      "name": "Lepidomeda vittata",
      "kingdom": "ANIMALIA",
      "category": "Endangered",
      "popTrend": "Decreasing",
      "points": null
    },
    {
      "id": 18234234,
      "taxonID": 11576,
      "pubYear": 2014,
      "year": 2012,
      "name": "Lepidomeda albivallis",
      "kingdom": "ANIMALIA",
      "category": "Critically Endangered",
      "popTrend": "Increasing",
      "points": null
    },
    {
      "id": 18234340,
      "taxonID": 8709,
      "pubYear": 2013,
      "year": 2012,
      "name": "Fundulus waccamensis",
      "kingdom": "ANIMALIA",
      "category": "Vulnerable",
      "popTrend": "Stable",
      "points": null
    },
    {
      "id": 18234591,
      "taxonID": 202107,
      "pubYear": 2013,
      "year": 2012,
      "name": "Gila orcuttii",
      "kingdom": "ANIMALIA",
      "category": "Vulnerable",
      "popTrend": "Decreasing",
      "points": null
    },
    {
      "id": 18235096,
      "taxonID": 202538,
      "pubYear": 2013,
      "year": 2012,
      "name": "Etheostoma susanae",
      "kingdom": "ANIMALIA",
      "category": "Endangered",
      "popTrend": "Decreasing",
      "points": null
    },
    {
      "id": 18235139,
      "taxonID": 8130,
      "pubYear": 2013,
      "year": 2012,
      "name": "Etheostoma striatulum",
      "kingdom": "ANIMALIA",
      "category": "Vulnerable",
      "popTrend": "Decreasing",
      "points": null
    },
    {
      "id": 18235396,
      "taxonID": 9182,
      "pubYear": 2014,
      "year": 2012,
      "name": "Siphateles boraxobius",
      "kingdom": "ANIMALIA",
      "category": "Vulnerable",
      "popTrend": "Stable",
      "points": null
    },
    {
      "id": 18235460,
      "taxonID": 11207,
      "pubYear": 2013,
      "year": 2012,
      "name": "Lampetra hubbsi",
      "kingdom": "ANIMALIA",
      "category": "Vulnerable",
      "popTrend": "Decreasing",
      "points": null
    },
    {
      "id": 18236094,
      "taxonID": 8131,
      "pubYear": 2013,
      "year": 2012,
      "name": "Etheostoma trisella",
      "kingdom": "ANIMALIA",
      "category": "Vulnerable",
      "popTrend": "Stable",
      "points": null
    },
    {
      "id": 18236876,
      "taxonID": 202384,
      "pubYear": 2013,
      "year": 2012,
      "name": "Fundulus euryzonus",
      "kingdom": "ANIMALIA",
      "category": "Vulnerable",
      "popTrend": "Decreasing",
      "points": null
    },
    {
      "id": 1408337,
      "taxonID": 17398,
      "pubYear": 2012,
      "year": 2012,
      "name": "Pisidium sanguinichristi",
      "kingdom": "ANIMALIA",
      "category": "Vulnerable",
      "popTrend": "Stable",
      "points": null
    },
    {
      "id": 1414101,
      "taxonID": 174471,
      "pubYear": 2012,
      "year": 2012,
      "name": "Brachylophus bulabula",
      "kingdom": "ANIMALIA",
      "category": "Endangered",
      "popTrend": "Decreasing",
      "points": null
    },
    {
      "id": 19032145,
      "taxonID": 202154,
      "pubYear": 2013,
      "year": 2012,
      "name": "Macrhybopsis tetranema",
      "kingdom": "ANIMALIA",
      "category": "Endangered",
      "popTrend": "Decreasing",
      "points": null
    },
    {
      "id": 19032220,
      "taxonID": 202279,
      "pubYear": 2013,
      "year": 2012,
      "name": "Notropis albizonatus",
      "kingdom": "ANIMALIA",
      "category": "Endangered",
      "popTrend": "Decreasing",
      "points": null
    },
    {
      "id": 19032246,
      "taxonID": 14893,
      "pubYear": 2013,
      "year": 2012,
      "name": "Notropis perpallidus",
      "kingdom": "ANIMALIA",
      "category": "Vulnerable",
      "popTrend": "Decreasing",
      "points": null
    },
    {
      "id": 19032625,
      "taxonID": 23162,
      "pubYear": 2013,
      "year": 2012,
      "name": "Xyrauchen texanus",
      "kingdom": "ANIMALIA",
      "category": "Critically Endangered",
      "popTrend": "Decreasing",
      "points": null
    },
    {
      "id": 19032702,
      "taxonID": 14888,
      "pubYear": 2013,
      "year": 2012,
      "name": "Notropis mekistocholas",
      "kingdom": "ANIMALIA",
      "category": "Endangered",
      "popTrend": "Decreasing",
      "points": null
    },
    {
      "id": 19032854,
      "taxonID": 16589,
      "pubYear": 2013,
      "year": 2012,
      "name": "Percina jenkinsi",
      "kingdom": "ANIMALIA",
      "category": "Critically Endangered",
      "popTrend": "Decreasing",
      "points": null
    },
    {
      "id": 19032955,
      "taxonID": 15454,
      "pubYear": 2013,
      "year": 2012,
      "name": "Oregonichthys kalawatseti",
      "kingdom": "ANIMALIA",
      "category": "Vulnerable",
      "popTrend": "Decreasing",
      "points": null
    },
    {
      "id": 19032981,
      "taxonID": 14884,
      "pubYear": 2013,
      "year": 2012,
      "name": "Notropis cahabae",
      "kingdom": "ANIMALIA",
      "category": "Endangered",
      "popTrend": "Decreasing",
      "points": null
    },
    {
      "id": 19033087,
      "taxonID": 16586,
      "pubYear": 2013,
      "year": 2012,
      "name": "Percina aurolineata",
      "kingdom": "ANIMALIA",
      "category": "Vulnerable",
      "popTrend": "Decreasing",
      "points": null
    },
    {
      "id": 19033136,
      "taxonID": 16594,
      "pubYear": 2013,
      "year": 2012,
      "name": "Percina rex",
      "kingdom": "ANIMALIA",
      "category": "Vulnerable",
      "popTrend": "Increasing",
      "points": null
    },
    {
      "id": 19033623,
      "taxonID": 16593,
      "pubYear": 2014,
      "year": 2012,
      "name": "Percina pantherina",
      "kingdom": "ANIMALIA",
      "category": "Endangered",
      "popTrend": "Stable",
      "points": null
    },
    {
      "id": 19033649,
      "taxonID": 16595,
      "pubYear": 2013,
      "year": 2012,
      "name": "Percina tanasi",
      "kingdom": "ANIMALIA",
      "category": "Vulnerable",
      "popTrend": "Stable",
      "points": null
    },
    {
      "id": 19033751,
      "taxonID": 14900,
      "pubYear": 2013,
      "year": 2012,
      "name": "Noturus flavipinnis",
      "kingdom": "ANIMALIA",
      "category": "Vulnerable",
      "popTrend": "Stable",
      "points": null
    },
    {
      "id": 19033831,
      "taxonID": 202594,
      "pubYear": 2013,
      "year": 2012,
      "name": "Percina sipsi",
      "kingdom": "ANIMALIA",
      "category": "Vulnerable",
      "popTrend": "Stable",
      "points": null
    },
    {
      "id": 19033884,
      "taxonID": 14898,
      "pubYear": 2013,
      "year": 2012,
      "name": "Pteronotropis welaka",
      "kingdom": "ANIMALIA",
      "category": "Vulnerable",
      "popTrend": "Decreasing",
      "points": null
    },
    {
      "id": 19033960,
      "taxonID": 202302,
      "pubYear": 2013,
      "year": 2012,
      "name": "Notropis girardi",
      "kingdom": "ANIMALIA",
      "category": "Vulnerable",
      "popTrend": "Decreasing",
      "points": null
    },
    {
      "id": 19033986,
      "taxonID": 20467,
      "pubYear": 2013,
      "year": 2012,
      "name": "Speoplatyrhinus poulsoni",
      "kingdom": "ANIMALIA",
      "category": "Critically Endangered",
      "popTrend": "Stable",
      "points": null
    },
    {
      "id": 19034065,
      "taxonID": 12923,
      "pubYear": 2013,
      "year": 2012,
      "name": "Meda fulgida",
      "kingdom": "ANIMALIA",
      "category": "Endangered",
      "popTrend": "Decreasing",
      "points": null
    },
    {
      "id": 19034168,
      "taxonID": 14899,
      "pubYear": 2013,
      "year": 2012,
      "name": "Noturus baileyi",
      "kingdom": "ANIMALIA",
      "category": "Vulnerable",
      "popTrend": "Stable",
      "points": null
    },
    {
      "id": 19034295,
      "taxonID": 17468,
      "pubYear": 2013,
      "year": 2012,
      "name": "Plagopterus argentissimus",
      "kingdom": "ANIMALIA",
      "category": "Critically Endangered",
      "popTrend": "Decreasing",
      "points": null
    },
    {
      "id": 19034371,
      "taxonID": 18829,
      "pubYear": 2013,
      "year": 2012,
      "name": "Ptychocheilus lucius",
      "kingdom": "ANIMALIA",
      "category": "Vulnerable",
      "popTrend": "Stable",
      "points": null
    },
    {
      "id": 19034397,
      "taxonID": 16588,
      "pubYear": 2013,
      "year": 2012,
      "name": "Percina cymatotaenia",
      "kingdom": "ANIMALIA",
      "category": "Vulnerable",
      "popTrend": "Stable",
      "points": null
    },
    {
      "id": 19034477,
      "taxonID": 13146,
      "pubYear": 2014,
      "year": 2012,
      "name": "Menidia extensa",
      "kingdom": "ANIMALIA",
      "category": "Vulnerable",
      "popTrend": "Stable",
      "points": null
    },
    {
      "id": 19034582,
      "taxonID": 14904,
      "pubYear": 2013,
      "year": 2012,
      "name": "Noturus munitus",
      "kingdom": "ANIMALIA",
      "category": "Vulnerable",
      "popTrend": "Decreasing",
      "points": null
    },
    {
      "id": 19034660,
      "taxonID": 14895,
      "pubYear": 2013,
      "year": 2012,
      "name": "Notropis semperasper",
      "kingdom": "ANIMALIA",
      "category": "Vulnerable",
      "popTrend": "Decreasing",
      "points": null
    },
    {
      "id": 19034888,
      "taxonID": 202600,
      "pubYear": 2013,
      "year": 2012,
      "name": "Percina williamsi",
      "kingdom": "ANIMALIA",
      "category": "Vulnerable",
      "popTrend": "Decreasing",
      "points": null
    },
    {
      "id": 19035040,
      "taxonID": 14892,
      "pubYear": 2013,
      "year": 2012,
      "name": "Notropis oxyrhynchus",
      "kingdom": "ANIMALIA",
      "category": "Vulnerable",
      "popTrend": "Decreasing",
      "points": null
    },
    {
      "id": 19035066,
      "taxonID": 14907,
      "pubYear": 2013,
      "year": 2012,
      "name": "Noturus taylori",
      "kingdom": "ANIMALIA",
      "category": "Endangered",
      "popTrend": "Decreasing",
      "points": null
    },
    {
      "id": 19035118,
      "taxonID": 13602,
      "pubYear": 2014,
      "year": 2012,
      "name": "Moapa coriacea",
      "kingdom": "ANIMALIA",
      "category": "Critically Endangered",
      "popTrend": "Decreasing",
      "points": null
    },
    {
      "id": 19086055,
      "taxonID": 178352,
      "pubYear": 2013,
      "year": 2012,
      "name": "Chioninia vaillantii",
      "kingdom": "ANIMALIA",
      "category": "Endangered",
      "popTrend": "Decreasing",
      "points": null
    },
    {
      "id": 1414514,
      "taxonID": 174477,
      "pubYear": 2012,
      "year": 2012,
      "name": "Ctenosaura nolascensis",
      "kingdom": "ANIMALIA",
      "category": "Vulnerable",
      "popTrend": "Stable",
      "points": null
    },
    {
      "id": 1436487,
      "taxonID": 176251,
      "pubYear": 2019,
      "year": 2012,
      "name": "Celestus scansorius",
      "kingdom": "ANIMALIA",
      "category": "Endangered",
      "popTrend": "Decreasing",
      "points": null
    },
    {
      "id": 1443222,
      "taxonID": 17666,
      "pubYear": 2012,
      "year": 2012,
      "name": "Pleurobema curtum",
      "kingdom": "ANIMALIA",
      "category": "Critically Endangered",
      "popTrend": "Decreasing",
      "points": null
    },
    {
      "id": 1443931,
      "taxonID": 17671,
      "pubYear": 2012,
      "year": 2012,
      "name": "Pleurobema taitianum",
      "kingdom": "ANIMALIA",
      "category": "Endangered",
      "popTrend": "Decreasing",
      "points": null
    },
    {
      "id": 1447123,
      "taxonID": 17679,
      "pubYear": 2012,
      "year": 2012,
      "name": "Pleurobema decisum",
      "kingdom": "ANIMALIA",
      "category": "Endangered",
      "popTrend": "Decreasing",
      "points": null
    },
    {
      "id": 1450114,
      "taxonID": 17685,
      "pubYear": 2012,
      "year": 2012,
      "name": "Pleurobema hanleyianum",
      "kingdom": "ANIMALIA",
      "category": "Critically Endangered",
      "popTrend": "Decreasing",
      "points": null
    },
    {
      "id": 1452398,
      "taxonID": 17690,
      "pubYear": 2012,
      "year": 2012,
      "name": "Pleurobema pyriforme",
      "kingdom": "ANIMALIA",
      "category": "Endangered",
      "popTrend": "Decreasing",
      "points": null
    },
    {
      "id": 1453947,
      "taxonID": 17692,
      "pubYear": 2012,
      "year": 2012,
      "name": "Pleurobema rubellum",
      "kingdom": "ANIMALIA",
      "category": "Critically Endangered",
      "popTrend": "Decreasing",
      "points": null
    },
    {
      "id": 1459743,
      "taxonID": 17699,
      "pubYear": 2012,
      "year": 2012,
      "name": "Pleurocera corpulenta",
      "kingdom": "ANIMALIA",
      "category": "Critically Endangered",
      "popTrend": "Decreasing",
      "points": null
    },
    {
      "id": 21576772,
      "taxonID": 21460622,
      "pubYear": 2014,
      "year": 2012,
      "name": "Ibalonius bimaculatus",
      "kingdom": "ANIMALIA",
      "category": "Endangered",
      "popTrend": "Stable",
      "points": null
    },
    {
      "id": 21577993,
      "taxonID": 196761,
      "pubYear": 2014,
      "year": 2012,
      "name": "Ibalonius inscriptus",
      "kingdom": "ANIMALIA",
      "category": "Endangered",
      "popTrend": "Decreasing",
      "points": null
    },
    {
      "id": 21954429,
      "taxonID": 11162,
      "pubYear": 2016,
      "year": 2012,
      "name": "Lagorchestes hirsutus",
      "kingdom": "ANIMALIA",
      "category": "Vulnerable",
      "popTrend": "Stable",
      "points": null
    },
    {
      "id": 115100163,
      "taxonID": 10863,
      "pubYear": 2016,
      "year": 2012,
      "name": "Isoodon auratus",
      "kingdom": "ANIMALIA",
      "category": "Vulnerable",
      "popTrend": "Decreasing",
      "points": null
    },
    {
      "id": 21961347,
      "taxonID": 2785,
      "pubYear": 2016,
      "year": 2012,
      "name": "Bettongia penicillata",
      "kingdom": "ANIMALIA",
      "category": "Critically Endangered",
      "popTrend": "Decreasing",
      "points": null
    },
    {
      "id": 1462005,
      "taxonID": 17701,
      "pubYear": 2012,
      "year": 2012,
      "name": "Pleurocera foremani",
      "kingdom": "ANIMALIA",
      "category": "Endangered",
      "popTrend": "Decreasing",
      "points": null
    },
    {
      "id": 1485231,
      "taxonID": 177425,
      "pubYear": 2013,
      "year": 2012,
      "name": "Omoadiphas texiguatensis",
      "kingdom": "ANIMALIA",
      "category": "Critically Endangered",
      "popTrend": "Decreasing",
      "points": null
    },
    {
      "id": 2767821,
      "taxonID": 203526,
      "pubYear": 2014,
      "year": 2012,
      "name": "Geophis fulvoguttatus",
      "kingdom": "ANIMALIA",
      "category": "Endangered",
      "popTrend": "Decreasing",
      "points": null
    },
    {
      "id": 1487908,
      "taxonID": 177486,
      "pubYear": 2013,
      "year": 2012,
      "name": "Micrurus ruatanus",
      "kingdom": "ANIMALIA",
      "category": "Critically Endangered",
      "popTrend": "Decreasing",
      "points": null
    },
    {
      "id": 2766810,
      "taxonID": 203508,
      "pubYear": 2013,
      "year": 2012,
      "name": "Enulius roatenensis",
      "kingdom": "ANIMALIA",
      "category": "Endangered",
      "popTrend": "Decreasing",
      "points": null
    },
    {
      "id": 509782,
      "taxonID": 12803,
      "pubYear": 2012,
      "year": 2012,
      "name": "Margaritifera hembeli",
      "kingdom": "ANIMALIA",
      "category": "Critically Endangered",
      "popTrend": "Decreasing",
      "points": null
    },
    {
      "id": 2773186,
      "taxonID": 20707,
      "pubYear": 2012,
      "year": 2012,
      "name": "Stagnicola bonnevillensis",
      "kingdom": "ANIMALIA",
      "category": "Critically Endangered",
      "popTrend": "Decreasing",
      "points": null
    },
    {
      "id": 510370,
      "taxonID": 12927,
      "pubYear": 2012,
      "year": 2012,
      "name": "Medionidus parvulus",
      "kingdom": "ANIMALIA",
      "category": "Endangered",
      "popTrend": "Decreasing",
      "points": null
    },
    {
      "id": 510583,
      "taxonID": 12930,
      "pubYear": 2012,
      "year": 2012,
      "name": "Medionidus walkeri",
      "kingdom": "ANIMALIA",
      "category": "Critically Endangered",
      "popTrend": "Decreasing",
      "points": null
    },
    {
      "id": 2765014,
      "taxonID": 203418,
      "pubYear": 2015,
      "year": 2012,
      "name": "Garra mamshuqa",
      "kingdom": "ANIMALIA",
      "category": "Endangered",
      "popTrend": "Decreasing",
      "points": null
    },
    {
      "id": 2765007,
      "taxonID": 203417,
      "pubYear": 2015,
      "year": 2012,
      "name": "Garra lautior",
      "kingdom": "ANIMALIA",
      "category": "Endangered",
      "popTrend": "Decreasing",
      "points": null
    },
    {
      "id": 502085,
      "taxonID": 11250,
      "pubYear": 2012,
      "year": 2012,
      "name": "Hamiota altilis",
      "kingdom": "ANIMALIA",
      "category": "Endangered",
      "popTrend": "Decreasing",
      "points": null
    },
    {
      "id": 2706807,
      "taxonID": 201481,
      "pubYear": 2014,
      "year": 2012,
      "name": "Sechelleptus seychellarum",
      "kingdom": "ANIMALIA",
      "category": "Endangered",
      "popTrend": "Decreasing",
      "points": null
    },
    {
      "id": 2706751,
      "taxonID": 201469,
      "pubYear": 2014,
      "year": 2012,
      "name": "Rhinotus vanmoli",
      "kingdom": "ANIMALIA",
      "category": "Endangered",
      "popTrend": "Decreasing",
      "points": null
    },
    {
      "id": 2706145,
      "taxonID": 201419,
      "pubYear": 2014,
      "year": 2012,
      "name": "Sechelliosoma forcipatum",
      "kingdom": "ANIMALIA",
      "category": "Endangered",
      "popTrend": "Stable",
      "points": null
    },
    {
      "id": 2605933,
      "taxonID": 199600,
      "pubYear": 2013,
      "year": 2012,
      "name": "Uromastyx thomasi",
      "kingdom": "ANIMALIA",
      "category": "Vulnerable",
      "popTrend": "Decreasing",
      "points": null
    },
    {
      "id": 2765000,
      "taxonID": 203416,
      "pubYear": 2015,
      "year": 2012,
      "name": "Garra buettikeri",
      "kingdom": "ANIMALIA",
      "category": "Vulnerable",
      "popTrend": "Decreasing",
      "points": null
    },
    {
      "id": 2764944,
      "taxonID": 203408,
      "pubYear": 2015,
      "year": 2012,
      "name": "Carasobarbus exulatus",
      "kingdom": "ANIMALIA",
      "category": "Endangered",
      "popTrend": "Decreasing",
      "points": null
    },
    {
      "id": 2764937,
      "taxonID": 203407,
      "pubYear": 2015,
      "year": 2012,
      "name": "Carasobarbus apoensis",
      "kingdom": "ANIMALIA",
      "category": "Endangered",
      "popTrend": "Decreasing",
      "points": null
    },
    {
      "id": 2774433,
      "taxonID": 20,
      "pubYear": 2013,
      "year": 2012,
      "name": "Abronia montecristoi",
      "kingdom": "ANIMALIA",
      "category": "Endangered",
      "popTrend": "Decreasing",
      "points": null
    },
    {
      "id": 2768983,
      "taxonID": 203592,
      "pubYear": 2014,
      "year": 2012,
      "name": "Sibon lamari",
      "kingdom": "ANIMALIA",
      "category": "Endangered",
      "popTrend": "Decreasing",
      "points": null
    },
    {
      "id": 2764923,
      "taxonID": 203404,
      "pubYear": 2015,
      "year": 2012,
      "name": "Acanthobrama hadiyahensis",
      "kingdom": "ANIMALIA",
      "category": "Critically Endangered",
      "popTrend": "Decreasing",
      "points": null
    },
    {
      "id": 2764105,
      "taxonID": 203332,
      "pubYear": 2014,
      "year": 2012,
      "name": "Tantilla tritaeniata",
      "kingdom": "ANIMALIA",
      "category": "Critically Endangered",
      "popTrend": "Decreasing",
      "points": null
    },
    {
      "id": 2763612,
      "taxonID": 203305,
      "pubYear": 2013,
      "year": 2012,
      "name": "Oxybelis wilsoni",
      "kingdom": "ANIMALIA",
      "category": "Endangered",
      "popTrend": "Decreasing",
      "points": null
    },
    {
      "id": 2759895,
      "taxonID": 203074,
      "pubYear": 2014,
      "year": 2012,
      "name": "Phyllodactylus insularis",
      "kingdom": "ANIMALIA",
      "category": "Vulnerable",
      "popTrend": "Decreasing",
      "points": null
    },
    {
      "id": 2781049,
      "taxonID": 22013,
      "pubYear": 2012,
      "year": 2012,
      "name": "Toxolasma cylindrellus",
      "kingdom": "ANIMALIA",
      "category": "Critically Endangered",
      "popTrend": "Decreasing",
      "points": null
    },
    {
      "id": 2758837,
      "taxonID": 203035,
      "pubYear": 2014,
      "year": 2012,
      "name": "Celestus montanus",
      "kingdom": "ANIMALIA",
      "category": "Endangered",
      "popTrend": "Decreasing",
      "points": null
    },
    {
      "id": 2758653,
      "taxonID": 203024,
      "pubYear": 2013,
      "year": 2012,
      "name": "Celestus bivittatus",
      "kingdom": "ANIMALIA",
      "category": "Endangered",
      "popTrend": "Decreasing",
      "points": null
    },
    {
      "id": 2758618,
      "taxonID": 203019,
      "pubYear": 2013,
      "year": 2012,
      "name": "Abronia vasconcelosii",
      "kingdom": "ANIMALIA",
      "category": "Vulnerable",
      "popTrend": "Decreasing",
      "points": null
    },
    {
      "id": 2515715,
      "taxonID": 198205,
      "pubYear": 2013,
      "year": 2012,
      "name": "Macrobrachium acanthochirus",
      "kingdom": "ANIMALIA",
      "category": "Vulnerable",
      "popTrend": "Decreasing",
      "points": null
    },
    {
      "id": 2511912,
      "taxonID": 198101,
      "pubYear": 2013,
      "year": 2012,
      "name": "Macrobrachium tuxtlaense",
      "kingdom": "ANIMALIA",
      "category": "Vulnerable",
      "popTrend": "Stable",
      "points": null
    },
    {
      "id": 2768425,
      "taxonID": 203556,
      "pubYear": 2013,
      "year": 2012,
      "name": "Omoadiphas cannula",
      "kingdom": "ANIMALIA",
      "category": "Critically Endangered",
      "popTrend": "Decreasing",
      "points": null
    },
    {
      "id": 115063540,
      "taxonID": 2787,
      "pubYear": 2016,
      "year": 2012,
      "name": "Bettongia tropica",
      "kingdom": "ANIMALIA",
      "category": "Endangered",
      "popTrend": "Decreasing",
      "points": null
    },
    {
      "id": 22398445,
      "taxonID": 18549,
      "pubYear": 2016,
      "year": 2012,
      "name": "Pseudomys fieldi",
      "kingdom": "ANIMALIA",
      "category": "Vulnerable",
      "popTrend": "Stable",
      "points": null
    },
    {
      "id": 22398752,
      "taxonID": 18552,
      "pubYear": 2016,
      "year": 2012,
      "name": "Pseudomys novaehollandiae",
      "kingdom": "ANIMALIA",
      "category": "Vulnerable",
      "popTrend": "Decreasing",
      "points": null
    },
    {
      "id": 2769417,
      "taxonID": 203656,
      "pubYear": 2014,
      "year": 2012,
      "name": "Atropoides indomitus",
      "kingdom": "ANIMALIA",
      "category": "Endangered",
      "popTrend": "Decreasing",
      "points": null
    },
    {
      "id": 2769438,
      "taxonID": 203659,
      "pubYear": 2014,
      "year": 2012,
      "name": "Bothriechis marchi",
      "kingdom": "ANIMALIA",
      "category": "Endangered",
      "popTrend": "Decreasing",
      "points": null
    },
    {
      "id": 2768418,
      "taxonID": 203555,
      "pubYear": 2014,
      "year": 2012,
      "name": "Omoadiphas aurula",
      "kingdom": "ANIMALIA",
      "category": "Vulnerable",
      "popTrend": "Decreasing",
      "points": null
    },
    {
      "id": 2767923,
      "taxonID": 203529,
      "pubYear": 2014,
      "year": 2012,
      "name": "Geophis nephodrymus",
      "kingdom": "ANIMALIA",
      "category": "Vulnerable",
      "popTrend": "Decreasing",
      "points": null
    },
    {
      "id": 115304711,
      "taxonID": 164729,
      "pubYear": 2012,
      "year": 2012,
      "name": "Uromastyx aegyptia",
      "kingdom": "ANIMALIA",
      "category": "Vulnerable",
      "popTrend": "Decreasing",
      "points": null
    },
    {
      "id": 22605180,
      "taxonID": 188631,
      "pubYear": 2013,
      "year": 2012,
      "name": "Hucho taimen",
      "kingdom": "ANIMALIA",
      "category": "Vulnerable",
      "popTrend": "Decreasing",
      "points": null
    },
    {
      "id": 43184956,
      "taxonID": 43184845,
      "pubYear": 2013,
      "year": 2012,
      "name": "Acizzia veski",
      "kingdom": "ANIMALIA",
      "category": "Critically Endangered",
      "popTrend": "Decreasing",
      "points": null
    },
    {
      "id": 44051115,
      "taxonID": 41778,
      "pubYear": 2013,
      "year": 2012,
      "name": "Tayassu pecari",
      "kingdom": "ANIMALIA",
      "category": "Vulnerable",
      "popTrend": "Decreasing",
      "points": null
    },
    {
      "id": 2994409,
      "taxonID": 44275,
      "pubYear": 2012,
      "year": 2012,
      "name": "Cyclura lewisi",
      "kingdom": "ANIMALIA",
      "category": "Endangered",
      "popTrend": "Increasing",
      "points": null
    },
    {
      "id": 1677819,
      "taxonID": 18091,
      "pubYear": 2012,
      "year": 2012,
      "name": "Potamilus capax",
      "kingdom": "ANIMALIA",
      "category": "Vulnerable",
      "popTrend": "Decreasing",
      "points": null
    },
    {
      "id": 46251651,
      "taxonID": 46251646,
      "pubYear": 2014,
      "year": 2012,
      "name": "Microcebus marohita",
      "kingdom": "ANIMALIA",
      "category": "Critically Endangered",
      "popTrend": "Decreasing",
      "points": null
    },
    {
      "id": 166502262,
      "taxonID": 12436,
      "pubYear": 2020,
      "year": 2012,
      "name": "Lycaon pictus",
      "kingdom": "ANIMALIA",
      "category": "Endangered",
      "popTrend": "Decreasing",
      "points": null
    },
    {
      "id": 1835517,
      "taxonID": 187923,
      "pubYear": 2012,
      "year": 2012,
      "name": "Yasuhikotakia nigrolineata",
      "kingdom": "ANIMALIA",
      "category": "Vulnerable",
      "popTrend": "Decreasing",
      "points": null
    },
    {
      "id": 1855766,
      "taxonID": 18825,
      "pubYear": 2012,
      "year": 2012,
      "name": "Ptychobranchus greenii",
      "kingdom": "ANIMALIA",
      "category": "Endangered",
      "popTrend": "Decreasing",
      "points": null
    },
    {
      "id": 1855999,
      "taxonID": 18826,
      "pubYear": 2012,
      "year": 2012,
      "name": "Ptychobranchus jonesi",
      "kingdom": "ANIMALIA",
      "category": "Critically Endangered",
      "popTrend": "Decreasing",
      "points": null
    },
    {
      "id": 1924473,
      "taxonID": 189371,
      "pubYear": 2012,
      "year": 2012,
      "name": "Alasmidonta triangulata",
      "kingdom": "ANIMALIA",
      "category": "Endangered",
      "popTrend": "Decreasing",
      "points": null
    },
    {
      "id": 1928059,
      "taxonID": 189539,
      "pubYear": 2012,
      "year": 2012,
      "name": "Elliptio roanokensis",
      "kingdom": "ANIMALIA",
      "category": "Vulnerable",
      "popTrend": "Decreasing",
      "points": null
    },
    {
      "id": 1929459,
      "taxonID": 18960,
      "pubYear": 2012,
      "year": 2012,
      "name": "Pyrgulopsis bruneauensis",
      "kingdom": "ANIMALIA",
      "category": "Critically Endangered",
      "popTrend": "Decreasing",
      "points": null
    },
    {
      "id": 3048087,
      "taxonID": 5671,
      "pubYear": 2012,
      "year": 2012,
      "name": "Crocodylus siamensis",
      "kingdom": "ANIMALIA",
      "category": "Critically Endangered",
      "popTrend": "Decreasing",
      "points": null
    },
    {
      "id": 2475610,
      "taxonID": 196745,
      "pubYear": 2014,
      "year": 2012,
      "name": "Ariadna ustulata",
      "kingdom": "ANIMALIA",
      "category": "Critically Endangered",
      "popTrend": "Decreasing",
      "points": null
    },
    {
      "id": 2475474,
      "taxonID": 196738,
      "pubYear": 2014,
      "year": 2012,
      "name": "Pterozonium tropiphorum",
      "kingdom": "ANIMALIA",
      "category": "Endangered",
      "popTrend": "Decreasing",
      "points": null
    },
    {
      "id": 1929774,
      "taxonID": 18961,
      "pubYear": 2012,
      "year": 2012,
      "name": "Marstonia castor",
      "kingdom": "ANIMALIA",
      "category": "Critically Endangered",
      "popTrend": "Decreasing",
      "points": null
    },
    {
      "id": 3048281,
      "taxonID": 5672,
      "pubYear": 2016,
      "year": 2012,
      "name": "Crocodylus mindorensis",
      "kingdom": "ANIMALIA",
      "category": "Critically Endangered",
      "popTrend": "Decreasing",
      "points": null
    },
    {
      "id": 2458707,
      "taxonID": 196466,
      "pubYear": 2014,
      "year": 2012,
      "name": "Argyrodella pusillus",
      "kingdom": "ANIMALIA",
      "category": "Vulnerable",
      "popTrend": "Stable",
      "points": null
    },
    {
      "id": 2443234,
      "taxonID": 196267,
      "pubYear": 2014,
      "year": 2012,
      "name": "Sadies trifasciata",
      "kingdom": "ANIMALIA",
      "category": "Endangered",
      "popTrend": "Decreasing",
      "points": null
    },
    {
      "id": 2442723,
      "taxonID": 196124,
      "pubYear": 2014,
      "year": 2012,
      "name": "Conothele truncicola",
      "kingdom": "ANIMALIA",
      "category": "Critically Endangered",
      "popTrend": "Decreasing",
      "points": null
    },
    {
      "id": 1931339,
      "taxonID": 189659,
      "pubYear": 2012,
      "year": 2012,
      "name": "Elimia bellacrenata",
      "kingdom": "ANIMALIA",
      "category": "Critically Endangered",
      "popTrend": "Decreasing",
      "points": null
    },
    {
      "id": 1932107,
      "taxonID": 189675,
      "pubYear": 2012,
      "year": 2012,
      "name": "Neritina granosa",
      "kingdom": "ANIMALIA",
      "category": "Vulnerable",
      "popTrend": "Decreasing",
      "points": null
    },
    {
      "id": 1932266,
      "taxonID": 189676,
      "pubYear": 2012,
      "year": 2012,
      "name": "Juga occata",
      "kingdom": "ANIMALIA",
      "category": "Endangered",
      "popTrend": "Decreasing",
      "points": null
    },
    {
      "id": 1932644,
      "taxonID": 189681,
      "pubYear": 2012,
      "year": 2012,
      "name": "Pyrgulopsis ventricosa",
      "kingdom": "ANIMALIA",
      "category": "Critically Endangered",
      "popTrend": "Decreasing",
      "points": null
    },
    {
      "id": 123740392,
      "taxonID": 203561,
      "pubYear": 2019,
      "year": 2012,
      "name": "Rodriguesophis scriptorcibatus",
      "kingdom": "ANIMALIA",
      "category": "Endangered",
      "popTrend": "Decreasing",
      "points": null
    },
    {
      "id": 1932862,
      "taxonID": 189690,
      "pubYear": 2012,
      "year": 2012,
      "name": "Quadrula intermedia",
      "kingdom": "ANIMALIA",
      "category": "Endangered",
      "popTrend": "Decreasing",
      "points": null
    },
    {
      "id": 2372949,
      "taxonID": 195011,
      "pubYear": 2013,
      "year": 2012,
      "name": "Eleutherodactylus notidodes",
      "kingdom": "ANIMALIA",
      "category": "Endangered",
      "popTrend": "Decreasing",
      "points": null
    },
    {
      "id": 3078239,
      "taxonID": 5952,
      "pubYear": 2012,
      "year": 2012,
      "name": "Cumberlandia monodonta",
      "kingdom": "ANIMALIA",
      "category": "Endangered",
      "popTrend": "Decreasing",
      "points": null
    },
    {
      "id": 54036093,
      "taxonID": 9184,
      "pubYear": 2014,
      "year": 2012,
      "name": "Gila cypha",
      "kingdom": "ANIMALIA",
      "category": "Endangered",
      "popTrend": "Decreasing",
      "points": null
    },
    {
      "id": 1933309,
      "taxonID": 189694,
      "pubYear": 2012,
      "year": 2012,
      "name": "Physa zionis",
      "kingdom": "ANIMALIA",
      "category": "Vulnerable",
      "popTrend": "Stable",
      "points": null
    },
    {
      "id": 1939134,
      "taxonID": 18985,
      "pubYear": 2012,
      "year": 2012,
      "name": "Pyrgulopsis roswellensis",
      "kingdom": "ANIMALIA",
      "category": "Vulnerable",
      "popTrend": "Decreasing",
      "points": null
    },
    {
      "id": 1939293,
      "taxonID": 18988,
      "pubYear": 2012,
      "year": 2012,
      "name": "Pyrgulopsis thermalis",
      "kingdom": "ANIMALIA",
      "category": "Critically Endangered",
      "popTrend": "Stable",
      "points": null
    }
  ]
}